{"description": "\n<p>Although Unit Testing is a recommended practice for any software project, care has to be exercised such that testing yields the desired benefits. Bad programming practices in both test code and production code can make Unit Testing a nightmare. Maintenance of an overly complex test suite can easily become a burden to the project team.</p>\n<p>This session, given by the creator of PHPUnit, will shine a light on best practices when it comes to testing <span class=\"caps\">PHP</span> code.</p>\n", "title": "PHPUnit Best Practices", "start_time": "2010-07-22T16:30:00-07:00", "track_id": 7, "user_ids": [22], "room_id": 5, "end_time": "2010-07-22T17:10:00-07:00", "id": 261}