{"description": "\n<p>Build your own wave service. Google is open sourcing the lion&#8217;s share of the code that went into creating Google Wave to help bootstrap a network of federated providers. This talk will discuss the code that has been released, the state of federation, and the state of the specifications. We&#8217;ll review the architecture of the open source implementation, how you can plug it into your own use cases, and how you can participate in the project and evolution of the underlying specifications.</p>\n", "title": "Open Source Google Wave: Building Your Own Wave Provider", "start_time": "2010-07-22T17:20:00-07:00", "track_id": 11, "user_ids": [435, 441], "room_id": 7, "end_time": "2010-07-22T18:00:00-07:00", "id": 2139}